olca_ipc/__init__.py
olca_ipc/ipc.py
olca_ipc/protocol.py
olca_ipc/rest.py
olca_ipc/utree.py
olca_ipc-2.0.3.dist-info/LICENSE
olca_ipc-2.0.3.dist-info/METADATA
olca_ipc-2.0.3.dist-info/WHEEL
olca_ipc-2.0.3.dist-info/top_level.txt
olca_ipc-2.0.3.dist-info/RECORD
