Metadata-Version: 2.1
Name: olca-ipc
Version: 2.0.3
Summary: A package for calling openLCA functions from Python.
Project-URL: Homepage, https://github.com/GreenDelta/olca-ipc.py
Project-URL: Bug Tracker, https://github.com/GreenDelta/olca-ipc.py/issues
Keywords: openLCA,life cycle assessment,LCA
Classifier: Development Status :: 5 - Production/Stable
Classifier: Programming Language :: Python :: 3
Classifier: License :: OSI Approved :: Mozilla Public License 2.0 (MPL 2.0)
Classifier: Operating System :: OS Independent
Classifier: Environment :: Console
Classifier: Intended Audience :: Science/Research
Classifier: Topic :: Utilities
Requires-Python: >=3.11
License-File: LICENSE
Requires-Dist: olca-schema >=0.0.12
Requires-Dist: requests >=2.28.1
